requirements.txt
setup.py
django_postgres_matviews/__init__.py
django_postgres_matviews/classes.py
django_postgres_matviews/utils.py
django_postgres_matviews.egg-info/PKG-INFO
django_postgres_matviews.egg-info/SOURCES.txt
django_postgres_matviews.egg-info/dependency_links.txt
django_postgres_matviews.egg-info/requires.txt
django_postgres_matviews.egg-info/top_level.txt
django_postgres_matviews/management/__init__.py
django_postgres_matviews/management/commands/__init__.py
django_postgres_matviews/management/commands/drop_matview.py
django_postgres_matviews/management/commands/drop_matviews.py
django_postgres_matviews/management/commands/list_matviews.py
django_postgres_matviews/management/commands/refresh_matview.py
django_postgres_matviews/management/commands/refresh_matviews.py