Metadata-Version: 2.1
Name: django-postgres-matviews
Version: 2020.12.1
Summary: django postgres matviews utils and commands
Home-page: https://github.com/andrewp-as-is/django-postgres-matviews.py
License: Unlicense
Keywords: django postgres matviews
Platform: UNKNOWN
Classifier: Framework :: Django
Classifier: License :: Public Domain
Classifier: Operating System :: OS Independent
Classifier: Programming Language :: Python :: 3
